murmurai/SubtitlesProcessor.py
murmurai/__init__.py
murmurai/__main__.py
murmurai/alignment.py
murmurai/asr.py
murmurai/audio.py
murmurai/compat.py
murmurai/conjunctions.py
murmurai/diarize.py
murmurai/log_utils.py
murmurai/schema.py
murmurai/transcribe.py
murmurai/utils.py
murmurai/assets/mel_filters.npz
murmurai/assets/pytorch_model.bin
murmurai/vads/__init__.py
murmurai/vads/pyannote.py
murmurai/vads/silero.py
murmurai/vads/vad.py
murmurai_core-1.0.6.dist-info/METADATA
murmurai_core-1.0.6.dist-info/WHEEL
murmurai_core-1.0.6.dist-info/entry_points.txt
murmurai_core-1.0.6.dist-info/licenses/LICENSE
murmurai_core-1.0.6.dist-info/RECORD
