Metadata-Version: 2.4
Name: murmurai-core
Version: 1.0.6
Summary: Modern speech recognition with word-level timestamps and speaker diarization. Fork of WhisperX with torch 2.6+, pyannote 4.x compatibility.
Project-URL: Repository, https://github.com/namastexlabs/murmurai
Project-URL: Documentation, https://github.com/namastexlabs/murmurai#readme
Project-URL: Issues, https://github.com/namastexlabs/murmurai/issues
Author: Felipe Rosa, Namastex Labs
License: BSD-2-Clause
License-File: LICENSE
Keywords: asr,diarization,murmur,speech-recognition,transcription,whisper
Requires-Python: <3.14,>=3.10
Requires-Dist: av<16.0.0
Requires-Dist: ctranslate2>=4.5.0
Requires-Dist: faster-whisper>=1.1.1
Requires-Dist: imageio-ffmpeg>=0.4.9
Requires-Dist: nltk>=3.9.1
Requires-Dist: numpy<2.3.0,>=2.1.0
Requires-Dist: nvidia-cudnn-cu12>=9.1.0; sys_platform == 'linux'
Requires-Dist: omegaconf>=2.3.0
Requires-Dist: pandas<2.3.0,>=2.2.3
Requires-Dist: pyannote-audio>=4.0
Requires-Dist: torch>=2.9.0
Requires-Dist: torchaudio>=2.9.0
Requires-Dist: torchcodec>=0.8.1
Requires-Dist: transformers>=4.50.0
Provides-Extra: triton
Requires-Dist: triton>=3.3.0; (sys_platform == 'linux' and platform_machine == 'x86_64') and extra == 'triton'
